numerize_denumerize/__init__.py
numerize_denumerize/denumerize.py
numerize_denumerize/numerize.py
numerize_denumerize-0.0.6.dist-info/METADATA
numerize_denumerize-0.0.6.dist-info/WHEEL
numerize_denumerize-0.0.6.dist-info/licenses/LICENSE
numerize_denumerize-0.0.6.dist-info/RECORD
