Metadata-Version: 2.1
Name: numerize_denumerize
Version: 0.0.6
Summary: A simple and better version of numerize package that also denumerizes
Project-URL: Homepage, https://github.com/dheereshagrwal/numerize_denumerize
Project-URL: Bug Tracker, https://github.com/dheereshagrwal/numerize_denumerize/issues
Author-email: Dheeresh Agarwal <da11@iitbbs.ac.in>
License-File: LICENSE
Classifier: License :: OSI Approved :: MIT License
Classifier: Operating System :: OS Independent
Classifier: Programming Language :: Python :: 3
Requires-Python: >=3.7
